my_recommending/__init__.py
my_recommending/app.py
my_recommending/callbacks.py
my_recommending/catboost_info/catboost_training.json
my_recommending/catboost_info/learn/events.out.tfevents
my_recommending/catboost_info/learn_error.tsv
my_recommending/catboost_info/time_left.tsv
my_recommending/catboost_info/tmp/cat_feature_index.f3cb137f-f3e54e56-8c1a8588-e8fa790c.tmp
my_recommending/configs/als.yaml
my_recommending/configs/base_config.yaml
my_recommending/configs/baseline.yaml
my_recommending/configs/cat.yaml
my_recommending/configs/cat_aggregator.yaml
my_recommending/configs/cat_ml25.yaml
my_recommending/configs/implicit_mf.yaml
my_recommending/configs/implicit_nn.yaml
my_recommending/configs/mf.yaml
my_recommending/configs/movielens_cat.yaml
my_recommending/configs/my_mf.yaml
my_recommending/configs/my_mf_slim.yaml
my_recommending/configs/my_mf_slim_25m.yaml
my_recommending/configs/slim.yaml
my_recommending/configs/svd.yaml
my_recommending/configs/svd_ml25m.yaml
my_recommending/configs/sweeps/als.yaml
my_recommending/configs/sweeps/baseline.yaml
my_recommending/configs/sweeps/cat.yaml
my_recommending/configs/sweeps/implicit_mf.yaml
my_recommending/configs/sweeps/implicit_nn.yaml
my_recommending/configs/sweeps/mf.yaml
my_recommending/configs/sweeps/movielens_cat.yaml
my_recommending/configs/sweeps/my_mf.yaml
my_recommending/configs/sweeps/my_mf_slim.yaml
my_recommending/configs/sweeps/slim.yaml
my_recommending/configs/sweeps/svd.yaml
my_recommending/data.py
my_recommending/entrypoint.py
my_recommending/interface.py
my_recommending/lit.py
my_recommending/losses.py
my_recommending/main.py
my_recommending/maths.py
my_recommending/metrics.py
my_recommending/models/__init__.py
my_recommending/models/als.py
my_recommending/models/baseline.py
my_recommending/models/bpmf.py
my_recommending/models/cat.py
my_recommending/models/mf.py
my_recommending/models/slim.py
my_recommending/movielens/__init__.py
my_recommending/movielens/callbacks.py
my_recommending/movielens/cat.py
my_recommending-0.1.22.dist-info/LICENSE
my_recommending-0.1.22.dist-info/WHEEL
my_recommending-0.1.22.dist-info/METADATA
my_recommending-0.1.22.dist-info/RECORD
